webhook_receiver/__init__.py
webhook_receiver/flask_utils.py
webhook_receiver/github_webhooks.py
webhook_receiver/gitlab_webhooks.py
webhook_receiver/webhooks.py
webhook_receiver/event/__init__.py
webhooks/__init__.py
webhooks/flask_utils.py
webhooks/github_webhooks.py
webhooks/gitlab_webhooks.py
webhooks/webhooks.py
webhooks/event/__init__.py
webhook_receiver-0.0.2.dist-info/LICENSE
webhook_receiver-0.0.2.dist-info/METADATA
webhook_receiver-0.0.2.dist-info/WHEEL
webhook_receiver-0.0.2.dist-info/top_level.txt
webhook_receiver-0.0.2.dist-info/RECORD
